{
 "kind": "books#volumes",
 "totalItems": 1,
 "items": [
  {
   "kind": "books#volume",
   "id": "b08_vgAACAAJ",
   "etag": "gHyY5INm6mE",
   "selfLink": "https://www.googleapis.com/books/v1/volumes/b08_vgAACAAJ",
   "volumeInfo": {
    "title": "O CEREBRO DE ALTA PERFORMANCE",
    "authors": [
     "LUIZ FERNANDO GARCIA"
    ],
    "description": "Todos os dias você toma decisões, e todas elas têm algum nível de importância e poder de definir seu sucesso ou seu fracasso. Entretanto, quanto dessas decisões é consciente e racional? Quantas vezes perdemos o controle das situações e acabamos agindo por impulso, causando impressões erradas sem perceber? Você tem certeza de que sua percepção está alinhada com a realidade e que consegue usufruir do melhor das oportunidades? A alta performance da mente pode mudar o resultado de seus projetos e planos, e ela só depende de treinamento para ser alcançada. O segredo para usar o potencial total do aparelho mental está no treino das capacidades atribuídas ao nosso cérebro, e principalmente ao córtex pré-frontal, no qual o processo de julgamento de nossas decisões acontece. Ao controlar o juiz de nossas atitudes, somos donos de nossas percepções - e também das impressões que causamos nos outros, seja em uma apresentação, em um primeiro encontro ou em uma reunião decisiva.",
    "industryIdentifiers": [
     {
      "type": "ISBN_10",
      "identifier": "8573129085"
     },
     {
      "type": "ISBN_13",
      "identifier": "9788573129083"
     }
    ],
    "readingModes": {
     "text": false,
     "image": false
    },
    "pageCount": 216,
    "printType": "BOOK",
    "maturityRating": "NOT_MATURE",
    "allowAnonLogging": false,
    "contentVersion": "preview-1.0.0",
    "panelizationSummary": {
     "containsEpubBubbles": false,
     "containsImageBubbles": false
    },
    "language": "pt",
    "previewLink": "http://books.google.com.br/books?id=b08_vgAACAAJ&dq=isbn:9788573129083&hl=&cd=1&source=gbs_api",
    "infoLink": "http://books.google.com.br/books?id=b08_vgAACAAJ&dq=isbn:9788573129083&hl=&source=gbs_api",
    "canonicalVolumeLink": "https://books.google.com/books/about/O_CEREBRO_DE_ALTA_PERFORMANCE.html?hl=&id=b08_vgAACAAJ"
   },
   "saleInfo": {
    "country": "BR",
    "saleability": "NOT_FOR_SALE",
    "isEbook": false
   },
   "accessInfo": {
    "country": "BR",
    "viewability": "NO_PAGES",
    "embeddable": false,
    "publicDomain": false,
    "textToSpeechPermission": "ALLOWED",
    "epub": {
     "isAvailable": false
    },
    "pdf": {
     "isAvailable": false
    },
    "webReaderLink": "http://play.google.com/books/reader?id=b08_vgAACAAJ&hl=&printsec=frontcover&source=gbs_api",
    "accessViewStatus": "NONE",
    "quoteSharingAllowed": false
   },
   "searchInfo": {
    "textSnippet": "Descubra o poder da orientação para resultados e caminhe com Luiz Fernando Garcia pelos tesouros que você sequer imaginou que guardava."
   }
  }
 ]
}
