{
 "kind": "books#volumes",
 "totalItems": 1,
 "items": [
  {
   "kind": "books#volume",
   "id": "lpg-vgAACAAJ",
   "etag": "3sv5JBuu4zk",
   "selfLink": "https://www.googleapis.com/books/v1/volumes/lpg-vgAACAAJ",
   "volumeInfo": {
    "title": "EM BUSCA DE UM NOVO AMANHA",
    "authors": [
     "SIDNEY SHELDON",
     "TILLY BAGSHAWE",
     "MARIANA KOHNERT"
    ],
    "publishedDate": "2015-11-12",
    "description": "Tracy Whitney está de volta em uma trama repleta de paixão, suspense e reviravoltas de tirar o fôlego. Ao lado de Jeff Stevens, Tracy Whitney foi responsável por alguns dos maiores assaltos do mundo. Movida pela adrenalina que o perigo proporciona, ela sempre esteve à vontade com a vida de criminosa. Mas, quando ela e Jeff se casam, eles fazem um trato: deixar o passado de crimes para trás e formar uma família. Decidida a abandonar o crime e levar uma vida digna, Tracy se esforça para adaptar-se à nova rotina. Mas ela sente que falta algo para que seja realmente feliz: um bebê. Porém, à medida que os meses passam e a tão desejada gravidez não acontece, ela se sente cada vez mais infeliz. Quando uma misteriosa e envolvente mulher surge na vida do casal, a até então indestrutível parceria deles é abalada. Um belo dia, Jeff acorda e descobre que Tracy desapareceu. Por mais de dez anos, ele faz o possível para descobrir o paradeiro da amada mas, como o restante do mundo, acredita que ela esteja morta. Até que uma série de assassinatos leva um audacioso detetive francês a acreditar que a vigarista está envolvida nos crimes. Tracy Whitney está mais uma vez no centro de uma misteriosa trama. A diferença é que, agora, ela tem tudo a perder, inclusive o homem que não consegue esquecer.",
    "industryIdentifiers": [
     {
      "type": "ISBN_10",
      "identifier": "8501104531"
     },
     {
      "type": "ISBN_13",
      "identifier": "9788501104533"
     }
    ],
    "readingModes": {
     "text": false,
     "image": false
    },
    "pageCount": 480,
    "printType": "BOOK",
    "maturityRating": "NOT_MATURE",
    "allowAnonLogging": false,
    "contentVersion": "preview-1.0.0",
    "panelizationSummary": {
     "containsEpubBubbles": false,
     "containsImageBubbles": false
    },
    "language": "pt",
    "previewLink": "http://books.google.com.br/books?id=lpg-vgAACAAJ&dq=isbn:9788501104533&hl=&cd=1&source=gbs_api",
    "infoLink": "http://books.google.com.br/books?id=lpg-vgAACAAJ&dq=isbn:9788501104533&hl=&source=gbs_api",
    "canonicalVolumeLink": "https://books.google.com/books/about/EM_BUSCA_DE_UM_NOVO_AMANHA.html?hl=&id=lpg-vgAACAAJ"
   },
   "saleInfo": {
    "country": "BR",
    "saleability": "NOT_FOR_SALE",
    "isEbook": false
   },
   "accessInfo": {
    "country": "BR",
    "viewability": "NO_PAGES",
    "embeddable": false,
    "publicDomain": false,
    "textToSpeechPermission": "ALLOWED",
    "epub": {
     "isAvailable": false
    },
    "pdf": {
     "isAvailable": false
    },
    "webReaderLink": "http://play.google.com/books/reader?id=lpg-vgAACAAJ&hl=&printsec=frontcover&source=gbs_api",
    "accessViewStatus": "NONE",
    "quoteSharingAllowed": false
   },
   "searchInfo": {
    "textSnippet": "Tracy Whitney está de volta em uma trama repleta de paixão, suspense e reviravoltas de tirar o fôlego Ao lado de Jeff Stevens, Tracy Whitney foi responsável por alguns dos maiores assaltos do mundo."
   }
  }
 ]
}
