{
 "kind": "books#volumes",
 "totalItems": 1,
 "items": [
  {
   "kind": "books#volume",
   "id": "S5wvRwAACAAJ",
   "etag": "tW8kep++Z5g",
   "selfLink": "https://www.googleapis.com/books/v1/volumes/S5wvRwAACAAJ",
   "volumeInfo": {
    "title": "FITOENERGETICA",
    "subtitle": "A ENERGIA DAS PLANTAS NO EQUILIBRIO DA ALMA",
    "authors": [
     "BRUNO JOSE GIMENES"
    ],
    "description": "Este mostra um estudo sobre as propriedades energéticas das plantas e seus efeitos sobre os seres humanos, os animais, os ambientes e até as próprias plantas. 'Fitoenergética' é um livro que revela a origem das doenças mais comuns da humanidade, apresentando a energia das plantas como uma opção de cura, equilíbrio e elevação da consciência. Vai além, quando alerta que a sociedade está tratando a doença de forma equivocada, com foco na consequência e não na causa. Nesta obra, o leitor vai mergulhar na sabedoria da natureza presente no Reino Vegetal, aprendendo a terapia da energia sutil das plantas para equilíbrio da alma em todos os aspectos - físico, emocional, mental e espiritual.",
    "industryIdentifiers": [
     {
      "type": "ISBN_10",
      "identifier": "8577271803"
     },
     {
      "type": "ISBN_13",
      "identifier": "9788577271801"
     }
    ],
    "readingModes": {
     "text": false,
     "image": false
    },
    "pageCount": 304,
    "printType": "BOOK",
    "maturityRating": "NOT_MATURE",
    "allowAnonLogging": false,
    "contentVersion": "preview-1.0.0",
    "language": "pt",
    "previewLink": "http://books.google.com.br/books?id=S5wvRwAACAAJ&dq=isbn:9788577271801&hl=&cd=1&source=gbs_api",
    "infoLink": "http://books.google.com.br/books?id=S5wvRwAACAAJ&dq=isbn:9788577271801&hl=&source=gbs_api",
    "canonicalVolumeLink": "https://books.google.com/books/about/FITOENERGETICA.html?hl=&id=S5wvRwAACAAJ"
   },
   "saleInfo": {
    "country": "BR",
    "saleability": "NOT_FOR_SALE",
    "isEbook": false
   },
   "accessInfo": {
    "country": "BR",
    "viewability": "NO_PAGES",
    "embeddable": false,
    "publicDomain": false,
    "textToSpeechPermission": "ALLOWED",
    "epub": {
     "isAvailable": false
    },
    "pdf": {
     "isAvailable": false
    },
    "webReaderLink": "http://play.google.com/books/reader?id=S5wvRwAACAAJ&hl=&printsec=frontcover&source=gbs_api",
    "accessViewStatus": "NONE",
    "quoteSharingAllowed": false
   },
   "searchInfo": {
    "textSnippet": "Este mostra um estudo sobre as propriedades energéticas das plantas e seus efeitos sobre os seres humanos, os animais, os ambientes e até as próprias plantas."
   }
  }
 ]
}
