{
 "kind": "books#volumes",
 "totalItems": 1,
 "items": [
  {
   "kind": "books#volume",
   "id": "ctAHtAEACAAJ",
   "etag": "GjxLDOdD26s",
   "selfLink": "https://www.googleapis.com/books/v1/volumes/ctAHtAEACAAJ",
   "volumeInfo": {
    "title": "Amor Que Transforma",
    "authors": [
     "Lu Alckmin"
    ],
    "description": "Como superar a maior dor do mundo Um acidente de helicóptero transformou-se em comoção nacional. Um jovem piloto de avião, morre, juntamente com outros profissionais. Este jovem era Thomas, filho do governador de SP Geraldo Alckmin. Em Amor que transforma Lu Alckmin, esposa de Geraldo e primeira dama de São Paulo contará, pela ótica da mãe, como foram os momentos e toda a trajetória posterior ao trágico acidente. Como enfrentar esta dor inigualável, como recomeçar após uma tragédia sem precedentes, qual a importância da união familiar em todo esse processo, qual o legado e o ensinamento deixado por Thomas, como é possível transformar em amor ao próximo a maior dor do mundo. Estas e outras respostas estão expostas neste livro. Com relatos comoventes, fotos inéditas e muita emoção, aqui será possível entender como o amor, a fé e a união podem transformar dor em compaixão e tristeza em esperança.",
    "industryIdentifiers": [
     {
      "type": "ISBN_10",
      "identifier": "8542211367"
     },
     {
      "type": "ISBN_13",
      "identifier": "9788542211368"
     }
    ],
    "readingModes": {
     "text": false,
     "image": false
    },
    "pageCount": 192,
    "printType": "BOOK",
    "maturityRating": "NOT_MATURE",
    "allowAnonLogging": false,
    "contentVersion": "preview-1.0.0",
    "panelizationSummary": {
     "containsEpubBubbles": false,
     "containsImageBubbles": false
    },
    "language": "pt",
    "previewLink": "http://books.google.com.br/books?id=ctAHtAEACAAJ&dq=isbn:9788542211368&hl=&cd=1&source=gbs_api",
    "infoLink": "http://books.google.com.br/books?id=ctAHtAEACAAJ&dq=isbn:9788542211368&hl=&source=gbs_api",
    "canonicalVolumeLink": "https://books.google.com/books/about/Amor_Que_Transforma.html?hl=&id=ctAHtAEACAAJ"
   },
   "saleInfo": {
    "country": "BR",
    "saleability": "NOT_FOR_SALE",
    "isEbook": false
   },
   "accessInfo": {
    "country": "BR",
    "viewability": "NO_PAGES",
    "embeddable": false,
    "publicDomain": false,
    "textToSpeechPermission": "ALLOWED",
    "epub": {
     "isAvailable": false
    },
    "pdf": {
     "isAvailable": false
    },
    "webReaderLink": "http://play.google.com/books/reader?id=ctAHtAEACAAJ&hl=&printsec=frontcover&source=gbs_api",
    "accessViewStatus": "NONE",
    "quoteSharingAllowed": false
   },
   "searchInfo": {
    "textSnippet": "Em Amor que transforma Lu Alckmin, esposa de Geraldo e primeira dama de São Paulo contará, pela ótica da mãe, como foram os momentos e toda a trajetória posterior ao trágico acidente."
   }
  }
 ]
}
