{
 "kind": "books#volumes",
 "totalItems": 1,
 "items": [
  {
   "kind": "books#volume",
   "id": "EvAuQwAACAAJ",
   "etag": "Yd7TOjehyHo",
   "selfLink": "https://www.googleapis.com/books/v1/volumes/EvAuQwAACAAJ",
   "volumeInfo": {
    "title": "Desvendando os segredos da linguagem corporal",
    "authors": [
     "Allan Pease",
     "Barbara Pease"
    ],
    "publishedDate": "2005",
    "description": "Este guia procura ensinar como melhorar os relacionamentos, aumentando a capacidade de comunicação e de entendimento com as pessoas. Além disso, mostra ao leitor como - causar uma impressão positiva nas pessoas; ser bem-sucedido em entrevistas e negociações; saber se uma pessoa está disponível; criar vínculos rapidamente e obter a cooperação de alguém; tornar-se uma pessoa agradável e sociável; saber se uma pessoa está mentindo; ler nas entrelinhas; usar a linguagem corporal para conseguir o que deseja; reconhecer sinais amorosos e jogos de poder.",
    "industryIdentifiers": [
     {
      "type": "ISBN_10",
      "identifier": "8575421824"
     },
     {
      "type": "ISBN_13",
      "identifier": "9788575421826"
     }
    ],
    "readingModes": {
     "text": false,
     "image": false
    },
    "pageCount": 271,
    "printType": "BOOK",
    "categories": [
     "Body language"
    ],
    "averageRating": 4.0,
    "ratingsCount": 8,
    "maturityRating": "NOT_MATURE",
    "allowAnonLogging": false,
    "contentVersion": "preview-1.0.0",
    "language": "pt",
    "previewLink": "http://books.google.com.br/books?id=EvAuQwAACAAJ&dq=isbn:9788575421826&hl=&cd=1&source=gbs_api",
    "infoLink": "http://books.google.com.br/books?id=EvAuQwAACAAJ&dq=isbn:9788575421826&hl=&source=gbs_api",
    "canonicalVolumeLink": "https://books.google.com/books/about/Desvendando_os_segredos_da_linguagem_cor.html?hl=&id=EvAuQwAACAAJ"
   },
   "saleInfo": {
    "country": "BR",
    "saleability": "NOT_FOR_SALE",
    "isEbook": false
   },
   "accessInfo": {
    "country": "BR",
    "viewability": "NO_PAGES",
    "embeddable": false,
    "publicDomain": false,
    "textToSpeechPermission": "ALLOWED",
    "epub": {
     "isAvailable": false
    },
    "pdf": {
     "isAvailable": false
    },
    "webReaderLink": "http://play.google.com/books/reader?id=EvAuQwAACAAJ&hl=&printsec=frontcover&source=gbs_api",
    "accessViewStatus": "NONE",
    "quoteSharingAllowed": false
   },
   "searchInfo": {
    "textSnippet": "Em Desvendando os segredos da linguagem Allan e Barbara Pease esclarecem que 93% da comunicação humana é feita através de expressões faciais e movimentos do corpo."
   }
  }
 ]
}
