{
 "kind": "books#volumes",
 "totalItems": 1,
 "items": [
  {
   "kind": "books#volume",
   "id": "R_OWswEACAAJ",
   "etag": "FcgcUxHdodo",
   "selfLink": "https://www.googleapis.com/books/v1/volumes/R_OWswEACAAJ",
   "volumeInfo": {
    "title": "Uma Noite Inesquecível",
    "subtitle": "AS QUATRO ESTAÇÕES DO AMOR",
    "authors": [
     "Lisa Kleypas",
     "Viviane Diniz"
    ],
    "description": "O Natal está se aproximando e Rafe Bowman acaba de chegar a Londres para uma união arranjada com Natalie Blandford. Com sua beleza estonteante e o físico imponente, ele tem certeza de que a linda aristocrata logo cairá a seus pés. No entanto, seus terríveis modos americanos e sua péssima reputação de farrista deixam Hannah, a prima da moça, chocada. Determinada a proteger Natalie, ela vai tornar a tarefa de cortejar a jovem muito mais difícil do que Rafe esperava. Hannah, porém, logo começa a se importar mais do que gostaria com o rude pretendente da prima. Rafe, por sua vez, passa a apreciar um pouco demais a companhia de Hannah, uma mulher forte e pragmática com um coração doce e gentil. E quando Daisy, Lillian, Annabelle e Evie, quatro amigas inseparáveis que já conseguiram encontrar o homem de seus sonhos, decidem agir como cupidos, quem sabe o que pode acontecer? Uma noite inesquecível é uma viagem mágica pela Londres vitoriana, com os diálogos espirituosos e personagens memoráveis que consagraram Lisa Kleypas como uma das autoras de romances de época mais aclamadas pelo público. Nesta continuação da série As Quatro Estações do Amor, os mais cínicos se tornam românticos e até os mais tímidos suspiram, arrebatados de paixão.",
    "industryIdentifiers": [
     {
      "type": "ISBN_10",
      "identifier": "8580417295"
     },
     {
      "type": "ISBN_13",
      "identifier": "9788580417296"
     }
    ],
    "readingModes": {
     "text": false,
     "image": false
    },
    "pageCount": 144,
    "printType": "BOOK",
    "maturityRating": "NOT_MATURE",
    "allowAnonLogging": false,
    "contentVersion": "preview-1.0.0",
    "panelizationSummary": {
     "containsEpubBubbles": false,
     "containsImageBubbles": false
    },
    "language": "pt",
    "previewLink": "http://books.google.com.br/books?id=R_OWswEACAAJ&dq=isbn:9788580417296&hl=&cd=1&source=gbs_api",
    "infoLink": "http://books.google.com.br/books?id=R_OWswEACAAJ&dq=isbn:9788580417296&hl=&source=gbs_api",
    "canonicalVolumeLink": "https://books.google.com/books/about/Uma_Noite_Inesquec%C3%ADvel.html?hl=&id=R_OWswEACAAJ"
   },
   "saleInfo": {
    "country": "BR",
    "saleability": "NOT_FOR_SALE",
    "isEbook": false
   },
   "accessInfo": {
    "country": "BR",
    "viewability": "NO_PAGES",
    "embeddable": false,
    "publicDomain": false,
    "textToSpeechPermission": "ALLOWED",
    "epub": {
     "isAvailable": false
    },
    "pdf": {
     "isAvailable": false
    },
    "webReaderLink": "http://play.google.com/books/reader?id=R_OWswEACAAJ&hl=&printsec=frontcover&source=gbs_api",
    "accessViewStatus": "NONE",
    "quoteSharingAllowed": false
   },
   "searchInfo": {
    "textSnippet": "Uma noite inesquecível é uma viagem mágica pela Londres vitoriana, com os diálogos espirituosos e personagens memoráveis que consagraram Lisa Kleypas como uma das autoras de romances de época mais aclamadas pelo público."
   }
  }
 ]
}
